deepomatic_oef-0.22.1-nspkg.pth
deepomatic/oef/__init__.py
deepomatic/oef/hyperparameter_dump.py
deepomatic/oef/api/__init__.py
deepomatic/oef/api/backbone.py
deepomatic/oef/api/experiment.py
deepomatic/oef/api/model.py
deepomatic/oef/configs/__init__.py
deepomatic/oef/configs/config_utils.py
deepomatic/oef/configs/model_args.py
deepomatic/oef/configs/model_list.py
deepomatic/oef/configs/model_list_generator.py
deepomatic/oef/configs/utils.py
deepomatic/oef/configs/image/__init__.py
deepomatic/oef/configs/image/backbones.py
deepomatic/oef/configs/image/utils.py
deepomatic/oef/configs/image/classification/__init__.py
deepomatic/oef/configs/image/classification/configs.py
deepomatic/oef/configs/image/detection/__init__.py
deepomatic/oef/configs/image/detection/efficientdet.py
deepomatic/oef/configs/image/detection/rcnn.py
deepomatic/oef/configs/image/detection/ssd.py
deepomatic/oef/configs/image/detection/yolo.py
deepomatic/oef/configs/image/ocr/__init__.py
deepomatic/oef/configs/image/ocr/attention.py
deepomatic/oef/configs/image/segmentation/__init__.py
deepomatic/oef/configs/image/segmentation/mask_rcnn.py
deepomatic/oef/platform/__init__.py
deepomatic/oef/platform/api.py
deepomatic/oef/platform/config.py
deepomatic/oef/platform/experiment_to_display_name.py
deepomatic/oef/platform/helpers/__init__.py
deepomatic/oef/platform/helpers/backends.json
deepomatic/oef/platform/helpers/common.py
deepomatic/oef/platform/helpers/controls.py
deepomatic/oef/platform/helpers/form.py
deepomatic/oef/platform/helpers/tags.py
deepomatic/oef/protos/__init__.py
deepomatic/oef/protos/dataoperation_pb2.py
deepomatic/oef/protos/dataset_dump_v1_pb2.py
deepomatic/oef/protos/dataset_dump_v2_pb2.py
deepomatic/oef/protos/dataset_pb2.py
deepomatic/oef/protos/experiment_pb2.py
deepomatic/oef/protos/hyperparameter_pb2.py
deepomatic/oef/protos/losses_pb2.py
deepomatic/oef/protos/optimizer_pb2.py
deepomatic/oef/protos/trainer_pb2.py
deepomatic/oef/protos/models/__init__.py
deepomatic_oef-0.22.1.dist-info/LICENSE
deepomatic_oef-0.22.1.dist-info/METADATA
deepomatic_oef-0.22.1.dist-info/WHEEL
deepomatic_oef-0.22.1.dist-info/namespace_packages.txt
deepomatic_oef-0.22.1.dist-info/top_level.txt
deepomatic_oef-0.22.1.dist-info/RECORD
