Metadata-Version: 2.1
Name: deepomatic-oef
Version: 0.22.1
Summary: Open Experiment Format
Home-page: https://github.com/Deepomatic/open-experiment-format
Author: Deepomatic
Author-email: support@deepomatic.com
License: MIT License
Project-URL: Product, https://deepomatic.com
Project-URL: Source, https://github.com/deepomatic/open-experiment-format
Project-URL: Tracker, https://github.com/deepomatic/open-experiment-format/issues
Platform: UNKNOWN
Classifier: Operating System :: OS Independent
Classifier: Programming Language :: Python :: 3
Requires-Python: >=2.7, !=3.0.*, !=3.1.*, !=3.2.*, !=3.3.*
License-File: LICENSE
Requires-Dist: protobuf (<5,>=3.8)
Requires-Dist: requests (>=2.19.1)
